tjutil/__init__.py
tjutil/hf_cache.py
tjutil/py.typed
tjutil-0.0.3.dist-info/METADATA
tjutil-0.0.3.dist-info/WHEEL
tjutil-0.0.3.dist-info/RECORD
