Metadata-Version: 2.4
Name: tjutil
Version: 0.0.3
Summary: utilities for python by qiuzhanghua
Author-email: qiuzhanghua <qiuzhanghua@icloud.com>
Requires-Python: >=3.8
